<?xml version="1.0" encoding="UTF-8"?>
<escenic version="2.0" xmlns="http://xmlns.escenic.com/2009/import">
    <content source="ece-auto-gen" sourceid="0eb71b8e-d1a5-4806-a5c3-f57202c15668" type="widget_viewPicker" state="published">
        <section-ref unique-name="config.default.tag.main.messi"/>
        <section-ref unique-name="config.default.tag.main.football" home-section="true"/>
        <relation type="viewRelation" source="ece-auto-gen" sourceid="d3579d76-5e04-4600-bfe1-adf9ed08f3c5"/>
        <priority value="0"/>
        <field name="title">Latest in home section of topic article</field>
        <field name="maxitems">5</field>
        <field name="datasource">{"settings":{"maxItems":"","endDate":"","publishingPeriod":"any","sort":"publish_date_dec","deduplication":"yes","24HoursBlock":"no","priority":"no","startDate":""},"sourceGroups":[{"sourceDefinition":[{"maxItems":"","sectionSelectionPolicy":"Category","sourceType":"list","endDate":"","publishingPeriod":"any","publication":"","section":"","sort":"publish_date_dec","contentTypes":["story"],"$$hashKey":"00G","includeSubsections":"yes","startDate":""}],"applySettings":"yes","$$hashKey":"00E"}],"sourceDefinition":[],"formatVersion":"3.1"}</field>
        <field name="gridstyle">{"wrapperClass":"row","gridItems":[{"style":"A"}],"repeatGrid":"2","styles":[{"classes":"","name":"A","$$hashKey":"004"}],"gridEditing":"basic"}</field>
        <field name="enableesi">false</field>
    </content>
</escenic>
